{
    "13oh6f6nNJ": {
        "id": "13oh6f6nNJ",
        "title": "Королёк - птичка певчая",
        "author": "ГЮНТЕКИН Решат Нури",
        "notes": "",
        "createdAt": "2019-03-24 20:11:54",
        "user": {
            "id": "102536471289425216982-google",
            "nickname": "Окс",
            "booksCount": 31
        }
    },
    "xEB3gZfS0_": {
        "id": "xEB3gZfS0_",
        "title": "Слушайте свое тело, вашего лучшего друга на Земле",
        "author": "БУРБО Лиз",
        "notes": "",
        "createdAt": "2019-03-24 20:07:51",
        "user": {
            "id": "102536471289425216982-google",
            "nickname": "Окс",
            "booksCount": 30
        }
    },
    "IxFPfPUlrp": {
        "id": "IxFPfPUlrp",
        "title": "Дочь Монтесумы",
        "author": "РАЙДЕР ХАГГАРД Генри",
        "notes": "",
        "createdAt": "2019-03-23 22:36:03",
        "user": {
            "id": "102536471289425216982-google",
            "nickname": "Окс",
            "booksCount": 29
        }
    },
    "sh0zaEHAdz": {
        "id": "sh0zaEHAdz",
        "title": "Пышечка",
        "author": "",
        "notes": "",
        "createdAt": "2019-03-23 18:32:47",
        "user": {
            "id": "13330781-vkontakte",
            "nickname": "le_brouillard",
            "booksCount": 96
        }
    },
    "6BA7PB87TS": {
        "id": "6BA7PB87TS",
        "title": "Старик и море",
        "author": "Хемингуэй Эрнест",
        "notes": "",
        "createdAt": "2019-03-23 11:23:30",
        "user": {
            "id": "13330781-vkontakte",
            "nickname": "le_brouillard",
            "booksCount": 95
        }
    },
    "RiF8Ny4AWS": {
        "id": "RiF8Ny4AWS",
        "title": "Дневник дебильного кота",
        "author": "Жуффа Сюзи, Пуйе Фредерик",
        "notes": "",
        "createdAt": "2019-03-23 08:43:16",
        "user": {
            "id": "13330781-vkontakte",
            "nickname": "le_brouillard",
            "booksCount": 94
        }
    },
    "-bSKI3qh9W": {
        "id": "-bSKI3qh9W",
        "title": "Тошнота",
        "author": "Сартр Жан Поль",
        "notes": "",
        "createdAt": "2019-03-22 20:23:39",
        "user": {
            "id": "10201286419319569-facebook",
            "nickname": "dininha",
            "booksCount": 14
        }
    },
    "BMhWzXUofn": {
        "id": "BMhWzXUofn",
        "title": "Афоризмы житейской мудрости",
        "author": "Шопенгауэр Артур",
        "notes": "пока самый любимый из известных мне философов",
        "createdAt": "2019-03-22 20:15:37",
        "user": {
            "id": "10201286419319569-facebook",
            "nickname": "dininha",
            "booksCount": 13
        }
    },
    "0FHvWByHTg": {
        "id": "0FHvWByHTg",
        "title": "Царь Эдип",
        "author": "Софокл",
        "notes": "",
        "createdAt": "2019-03-22 20:13:21",
        "user": {
            "id": "10201286419319569-facebook",
            "nickname": "dininha",
            "booksCount": 12
        }
    },
    "go_rylhy5D": {
        "id": "go_rylhy5D",
        "title": "Пир",
        "author": "Платон",
        "notes": "",
        "createdAt": "2019-03-22 20:12:20",
        "user": {
            "id": "10201286419319569-facebook",
            "nickname": "dininha",
            "booksCount": 11
        }
    },
    "vPObkQgXr7": {
        "id": "vPObkQgXr7",
        "title": "Белое на чёрном",
        "author": "Гальего Рубен",
        "notes": "",
        "createdAt": "2019-03-22 19:10:16",
        "user": {
            "id": "13330781-vkontakte",
            "nickname": "le_brouillard",
            "booksCount": 93
        }
    },
    "kOnxxSRxH3": {
        "id": "kOnxxSRxH3",
        "title": "Хорошие девочки не получают больших денег и хороших мужчин",
        "author": "Карен Финерман",
        "notes": "",
        "createdAt": "2019-03-22 17:50:54",
        "user": {
            "id": "2096581563762610-facebook",
            "nickname": "Таньчик",
            "booksCount": 10
        }
    },
    "lYUqczshdl": {
        "id": "lYUqczshdl",
        "title": "Привычка жениться",
        "author": "Сборник рассказов",
        "notes": "",
        "createdAt": "2019-03-22 17:49:46",
        "user": {
            "id": "2096581563762610-facebook",
            "nickname": "Таньчик",
            "booksCount": 9
        }
    },
    "srIqLK6tHu": {
        "id": "srIqLK6tHu",
        "title": "🧙🏻‍♂️ ПОСОХ И ШЛЯПА",
        "author": "Терри Пратчетт",
        "notes": "",
        "createdAt": "2019-03-22 16:14:36",
        "user": {
            "id": "158266434925901-facebook",
            "nickname": "GvenVivar ",
            "booksCount": 67
        }
    },
    "VuFFnIodf5": {
        "id": "VuFFnIodf5",
        "title": "Сам себе риэлтор.Как самостоятельно провести сделку с недвижимостью",
        "author": "Вадим Шабалин",
        "notes": "",
        "createdAt": "2019-03-22 09:51:04",
        "user": {
            "id": "68439978-vkontakte",
            "nickname": "kissamasya",
            "booksCount": 51
        }
    },
    "Kv41pFl1Kr": {
        "id": "Kv41pFl1Kr",
        "title": "За гранью времён",
        "author": "Лавкрафт Говард Филлипс",
        "notes": "Стиль отличается от алхимика. Местами наивное фэнтези,но все же не плохо.",
        "createdAt": "2019-03-22 06:12:25",
        "user": {
            "id": "10201286419319569-facebook",
            "nickname": "dininha",
            "booksCount": 10
        }
    },
    "SAH62hf1h_": {
        "id": "SAH62hf1h_",
        "title": "Единственная дочь",
        "author": "Снокстра Анна",
        "notes": "",
        "createdAt": "2019-03-21 18:58:03",
        "user": {
            "id": "13330781-vkontakte",
            "nickname": "le_brouillard",
            "booksCount": 92
        }
    },
    "m9od63dm-5": {
        "id": "m9od63dm-5",
        "title": "Внутренняя инженерия.",
        "author": "Садхгуру",
        "notes": "",
        "createdAt": "2019-03-21 15:24:19",
        "user": {
            "id": "10201286419319569-facebook",
            "nickname": "dininha",
            "booksCount": 9
        }
    },
    "GbyLByW0U7": {
        "id": "GbyLByW0U7",
        "title": "История Российского государства",
        "author": "Акунин",
        "notes": "",
        "createdAt": "2019-03-21 15:13:50",
        "user": {
            "id": "10201286419319569-facebook",
            "nickname": "dininha",
            "booksCount": 8
        }
    },
    "yA_nAyhppc": {
        "id": "yA_nAyhppc",
        "title": "Хюгге, или Уютное счастье по-датски.",
        "author": "Хелен Расселл",
        "notes": "Нудновато и много воды.",
        "createdAt": "2019-03-21 15:12:20",
        "user": {
            "id": "10201286419319569-facebook",
            "nickname": "dininha",
            "booksCount": 7
        }
    },
    "X80tHMCSW6": {
        "id": "X80tHMCSW6",
        "title": "Петр I",
        "author": "Толстой А.Н.",
        "notes": "Исторический роман о Петре и событиях той эпохи. Было интересно.",
        "createdAt": "2019-03-21 15:05:16",
        "user": {
            "id": "10201286419319569-facebook",
            "nickname": "dininha",
            "booksCount": 6
        }
    },
    "Xu8f6-MCWy": {
        "id": "Xu8f6-MCWy",
        "title": "Рассказы. Повести. Пьесы",
        "author": "Чехов А.П.",
        "notes": "Ну что тут сказать..гениальный  писатель он и есть гениальный писатель. Юмор неподражаем!",
        "createdAt": "2019-03-21 15:02:19",
        "user": {
            "id": "10201286419319569-facebook",
            "nickname": "dininha",
            "booksCount": 5
        }
    },
    "e4cSk_6lN2": {
        "id": "e4cSk_6lN2",
        "title": "Sapiens: Краткая история человечества",
        "author": "Харари Юваль Ной",
        "notes": "При чтении постоянное ощущение что все это уже было описано ранее в других источниках. Практически ничего нового не удалось почерпнуть.",
        "createdAt": "2019-03-21 14:58:36",
        "user": {
            "id": "10201286419319569-facebook",
            "nickname": "dininha",
            "booksCount": 4
        }
    },
    "DUP3g8clIO": {
        "id": "DUP3g8clIO",
        "title": "Наблюдая за англичанами",
        "author": "Фокс Кейт",
        "notes": "Книга очень интересная и полезная. Очень хорошо раскрывает характер ,традиции,образ мыслей  и привычки нации. Несмотря на то что написана потомственным антропологом,язык повествования не сложный для восприятия.",
        "createdAt": "2019-03-21 14:52:13",
        "user": {
            "id": "10201286419319569-facebook",
            "nickname": "dininha",
            "booksCount": 3
        }
    },
    "QEkiqGlRBZ": {
        "id": "QEkiqGlRBZ",
        "title": "Шантарам",
        "author": "Грегори Дэвид Робертс",
        "notes": "Не впечатлил.",
        "createdAt": "2019-03-21 14:46:58",
        "user": {
            "id": "10201286419319569-facebook",
            "nickname": "dininha",
            "booksCount": 2
        }
    },
    "kygpWO2IY9": {
        "id": "kygpWO2IY9",
        "title": "Алхмик",
        "author": "Лавкрафт Говард Филлипс",
        "notes": "Первая прочитанная из Лавкрафта. Очень понравилась живописная манера изложения.",
        "createdAt": "2019-03-21 14:45:30",
        "user": {
            "id": "10201286419319569-facebook",
            "nickname": "dininha",
            "booksCount": 1
        }
    },
    "Q5zt4ACvda": {
        "id": "Q5zt4ACvda",
        "title": "Нулевой номер",
        "author": "Умберто Эко",
        "notes": "",
        "createdAt": "2019-03-21 09:26:31",
        "user": {
            "id": "108113656204404967440-google",
            "nickname": "Janet",
            "booksCount": 688
        }
    },
    "yTSpewnG9E": {
        "id": "yTSpewnG9E",
        "title": "Игра кота 1-7",
        "author": "Роман Прокофьев",
        "notes": "Кот, 7 ключей, истинный огонь",
        "createdAt": "2019-03-20 17:02:36",
        "user": {
            "id": "12282474-vkontakte",
            "nickname": "Tr",
            "booksCount": 71
        }
    },
    "KB11hrWdf9": {
        "id": "KB11hrWdf9",
        "title": "Шум и ярость",
        "author": "Уильям Фолкнер",
        "notes": "читала, но с трудом помнится сюжет.",
        "createdAt": "2019-03-20 13:01:54",
        "user": {
            "id": "83788782-vkontakte",
            "nickname": "Ангелина",
            "booksCount": 57
        }
    },
    "t7lRko82Rs": {
        "id": "t7lRko82Rs",
        "title": "О дивный новый мир",
        "author": "Олдос Хаксли",
        "notes": "Слишком переоценёно, но в целом неплохо. Читалось медленно, но сейчас всё так читается. Всё это время читала немного, но просто не записывала.",
        "createdAt": "2019-03-20 12:51:20",
        "user": {
            "id": "83788782-vkontakte",
            "nickname": "Ангелина",
            "booksCount": 56
        }
    }
}