{
    "22376066-vkontakte": {
        "id": "22376066-vkontakte",
        "nickname": "anyutka_kozlova92",
        "booksCount": 1,
        "updatedAt": "2018-08-13 13:22:01"
    },
    "143278479-vkontakte": {
        "id": "143278479-vkontakte",
        "nickname": "Лина Кауфман",
        "booksCount": 25,
        "updatedAt": "2018-08-13 12:11:57"
    },
    "112254248549638795343-google": {
        "id": "112254248549638795343-google",
        "nickname": "German",
        "booksCount": 28,
        "updatedAt": "2018-08-13 06:01:40"
    },
    "100002563462782-facebook": {
        "id": "100002563462782-facebook",
        "nickname": "HXT",
        "booksCount": 322,
        "updatedAt": "2018-08-13 04:57:37"
    },
    "116961712580551399099-google": {
        "id": "116961712580551399099-google",
        "nickname": "violet_velva",
        "booksCount": 13,
        "updatedAt": "2018-08-12 19:12:54"
    },
    "108113656204404967440-google": {
        "id": "108113656204404967440-google",
        "nickname": "Janet",
        "booksCount": 663,
        "updatedAt": "2018-08-12 16:06:07"
    },
    "381417697-yandex": {
        "id": "381417697-yandex",
        "nickname": "me",
        "booksCount": 44,
        "updatedAt": "2018-08-12 14:22:47"
    },
    "241974816-vkontakte": {
        "id": "241974816-vkontakte",
        "nickname": "Ник Литвинов",
        "booksCount": 175,
        "updatedAt": "2018-08-12 14:06:15"
    },
    "100599204551896265722-google": {
        "id": "100599204551896265722-google",
        "nickname": "exulted",
        "booksCount": 80,
        "updatedAt": "2018-08-11 17:47:46"
    },
    "103293621948650602575-google": {
        "id": "103293621948650602575-google",
        "nickname": "Lost in Frost",
        "booksCount": 125,
        "updatedAt": "2018-08-11 17:03:54"
    },
    "176805114-yandex": {
        "id": "176805114-yandex",
        "nickname": "fir137",
        "booksCount": 2,
        "updatedAt": "2018-08-11 14:15:37"
    },
    "945973022276722-facebook": {
        "id": "945973022276722-facebook",
        "nickname": "Natalia Avramchuk",
        "booksCount": 0,
        "updatedAt": "2018-08-11 11:15:00"
    },
    "105831994080785626680-google": {
        "id": "105831994080785626680-google",
        "nickname": "Chiffi",
        "booksCount": 68,
        "updatedAt": "2018-08-10 18:27:23"
    },
    "15706320-vkontakte": {
        "id": "15706320-vkontakte",
        "nickname": "borodach",
        "booksCount": 133,
        "updatedAt": "2018-08-10 09:23:33"
    },
    "104505053912561500571-google": {
        "id": "104505053912561500571-google",
        "nickname": "mrs.Ekilei",
        "booksCount": 1,
        "updatedAt": "2018-08-10 06:23:31"
    },
    "220022778-vkontakte": {
        "id": "220022778-vkontakte",
        "nickname": "fox_mi",
        "booksCount": 23,
        "updatedAt": "2018-08-09 23:00:32"
    },
    "87639392-vkontakte": {
        "id": "87639392-vkontakte",
        "nickname": "veronika_vaha",
        "booksCount": 15,
        "updatedAt": "2018-08-09 21:26:28"
    },
    "32903202-vkontakte": {
        "id": "32903202-vkontakte",
        "nickname": "fire_ejik",
        "booksCount": 3,
        "updatedAt": "2018-08-09 19:35:09"
    },
    "118049897850017649660-google": {
        "id": "118049897850017649660-google",
        "nickname": "Sky",
        "booksCount": 101,
        "updatedAt": "2018-08-09 19:09:13"
    },
    "152488954-vkontakte": {
        "id": "152488954-vkontakte",
        "nickname": "kasikandriena",
        "booksCount": 46,
        "updatedAt": "2018-08-09 17:37:48"
    },
    "68439978-vkontakte": {
        "id": "68439978-vkontakte",
        "nickname": "kissamasya",
        "booksCount": 29,
        "updatedAt": "2018-08-09 09:52:46"
    },
    "184135339-vkontakte": {
        "id": "184135339-vkontakte",
        "nickname": "darb_el",
        "booksCount": 12,
        "updatedAt": "2018-08-09 04:11:25"
    },
    "21574100-vkontakte": {
        "id": "21574100-vkontakte",
        "nickname": "yn4k_wert",
        "booksCount": 1,
        "updatedAt": "2018-08-08 17:49:24"
    },
    "140966150-vkontakte": {
        "id": "140966150-vkontakte",
        "nickname": "mfevralev",
        "booksCount": 32,
        "updatedAt": "2018-08-08 11:51:03"
    },
    "73323849-yandex": {
        "id": "73323849-yandex",
        "nickname": "inna.besprozvannykh",
        "booksCount": 43,
        "updatedAt": "2018-08-08 10:48:44"
    },
    "30558181-vkontakte": {
        "id": "30558181-vkontakte",
        "nickname": "EsterHani",
        "booksCount": 154,
        "updatedAt": "2018-08-08 09:42:10"
    },
    "83820536-yandex": {
        "id": "83820536-yandex",
        "nickname": "lucius",
        "booksCount": 146,
        "updatedAt": "2018-08-08 02:57:38"
    },
    "52821952-vkontakte": {
        "id": "52821952-vkontakte",
        "nickname": "Apprentice ",
        "booksCount": 89,
        "updatedAt": "2018-08-06 20:49:41"
    },
    "117259947-yandex": {
        "id": "117259947-yandex",
        "nickname": "alexander.khanov",
        "booksCount": 5,
        "updatedAt": "2018-08-05 09:40:00"
    },
    "683897597-yandex": {
        "id": "683897597-yandex",
        "nickname": "asdf",
        "booksCount": 1,
        "updatedAt": "2018-08-04 12:15:05"
    }
}