{
    "371574201-vkontakte": {
        "id": "371574201-vkontakte",
        "nickname": "Deithwen",
        "booksCount": 11,
        "updatedAt": "2016-10-22 08:03:23"
    },
    "253918564-vkontakte": {
        "id": "253918564-vkontakte",
        "nickname": "yarikosimo",
        "booksCount": 0,
        "updatedAt": "2016-10-22 07:53:36"
    },
    "106616728662292831735-google": {
        "id": "106616728662292831735-google",
        "nickname": "Marsala",
        "booksCount": 0,
        "updatedAt": "2016-10-21 11:38:17"
    },
    "83788782-vkontakte": {
        "id": "83788782-vkontakte",
        "nickname": "Ангелина",
        "booksCount": 40,
        "updatedAt": "2016-10-21 11:21:36"
    },
    "87042697-vkontakte": {
        "id": "87042697-vkontakte",
        "nickname": "freezy_bi",
        "booksCount": 17,
        "updatedAt": "2016-10-20 20:56:22"
    },
    "7801383777140798509-mailru": {
        "id": "7801383777140798509-mailru",
        "nickname": "Александр Сергеев",
        "booksCount": 0,
        "updatedAt": "2016-10-20 20:42:13"
    },
    "1138852626183846-facebook": {
        "id": "1138852626183846-facebook",
        "nickname": "nadisvid",
        "booksCount": 18,
        "updatedAt": "2016-10-20 19:05:21"
    },
    "20565064-vkontakte": {
        "id": "20565064-vkontakte",
        "nickname": "Janet",
        "booksCount": 453,
        "updatedAt": "2016-10-20 12:38:24"
    },
    "1236741-vkontakte": {
        "id": "1236741-vkontakte",
        "nickname": "Olyaperekatipole",
        "booksCount": 60,
        "updatedAt": "2016-10-20 12:19:14"
    },
    "57248262-vkontakte": {
        "id": "57248262-vkontakte",
        "nickname": "shched.nova",
        "booksCount": 3,
        "updatedAt": "2016-10-20 12:16:31"
    },
    "243176966-vkontakte": {
        "id": "243176966-vkontakte",
        "nickname": "grigoryev_ivan",
        "booksCount": 1,
        "updatedAt": "2016-10-20 06:50:50"
    },
    "115622071-twitter": {
        "id": "115622071-twitter",
        "nickname": "rNix",
        "booksCount": 47,
        "updatedAt": "2016-10-20 01:36:28"
    },
    "380085691-vkontakte": {
        "id": "380085691-vkontakte",
        "nickname": "nohappinessnofun",
        "booksCount": 1,
        "updatedAt": "2016-10-19 16:00:49"
    },
    "364896871-vkontakte": {
        "id": "364896871-vkontakte",
        "nickname": "valdimarsdottir",
        "booksCount": 0,
        "updatedAt": "2016-10-19 12:26:15"
    },
    "12462836-vkontakte": {
        "id": "12462836-vkontakte",
        "nickname": "dmtrdmtr",
        "booksCount": 23,
        "updatedAt": "2016-10-18 20:32:09"
    },
    "278072338-vkontakte": {
        "id": "278072338-vkontakte",
        "nickname": "Арквейд Курапира",
        "booksCount": 41,
        "updatedAt": "2016-10-18 18:31:20"
    },
    "2352103981-twitter": {
        "id": "2352103981-twitter",
        "nickname": "Eji_tyan",
        "booksCount": 21,
        "updatedAt": "2016-10-18 15:15:57"
    },
    "15838562-vkontakte": {
        "id": "15838562-vkontakte",
        "nickname": "katalinamalkova",
        "booksCount": 0,
        "updatedAt": "2016-10-18 14:47:30"
    },
    "116164604589209895641-google": {
        "id": "116164604589209895641-google",
        "nickname": "Aleksandr",
        "booksCount": 0,
        "updatedAt": "2016-10-18 08:18:49"
    },
    "21138193-vkontakte": {
        "id": "21138193-vkontakte",
        "nickname": "dimapropolsky",
        "booksCount": 18,
        "updatedAt": "2016-10-17 16:12:27"
    },
    "110026466098031422803-google": {
        "id": "110026466098031422803-google",
        "nickname": "Citycat02",
        "booksCount": 0,
        "updatedAt": "2016-10-17 07:38:45"
    },
    "4899731-vkontakte": {
        "id": "4899731-vkontakte",
        "nickname": "kuzhakhmetov",
        "booksCount": 0,
        "updatedAt": "2016-10-16 18:03:44"
    },
    "152183909-vkontakte": {
        "id": "152183909-vkontakte",
        "nickname": "d.molokoedova",
        "booksCount": 0,
        "updatedAt": "2016-10-16 15:23:28"
    },
    "222677005-vkontakte": {
        "id": "222677005-vkontakte",
        "nickname": "Salamandrrra",
        "booksCount": 0,
        "updatedAt": "2016-10-16 12:24:24"
    },
    "1577468-vkontakte": {
        "id": "1577468-vkontakte",
        "nickname": "Беска",
        "booksCount": 5,
        "updatedAt": "2016-10-16 10:20:08"
    },
    "145516802-vkontakte": {
        "id": "145516802-vkontakte",
        "nickname": "ledera_hanako",
        "booksCount": 0,
        "updatedAt": "2016-10-15 12:33:35"
    },
    "100003094239547-facebook": {
        "id": "100003094239547-facebook",
        "nickname": "igor1980",
        "booksCount": 5,
        "updatedAt": "2016-10-15 05:30:57"
    },
    "64251996-vkontakte": {
        "id": "64251996-vkontakte",
        "nickname": "~ARHANGEL~",
        "booksCount": 42,
        "updatedAt": "2016-10-14 08:43:57"
    },
    "195257907510440-facebook": {
        "id": "195257907510440-facebook",
        "nickname": "valmac",
        "booksCount": 0,
        "updatedAt": "2016-10-13 22:17:43"
    },
    "357634987-vkontakte": {
        "id": "357634987-vkontakte",
        "nickname": "dealer_i",
        "booksCount": 0,
        "updatedAt": "2016-10-13 10:22:48"
    }
}