{
    "SYRVttOYDo": {
        "id": "SYRVttOYDo",
        "title": "Десять негритят",
        "author": "Агата Кристи",
        "notes": "",
        "createdAt": "2018-02-03 19:34:39",
        "user": {
            "id": "13935996761918642032-mailru",
            "nickname": "xaytennn",
            "booksCount": 16
        }
    },
    "U4hMne2QTq": {
        "id": "U4hMne2QTq",
        "title": "Империя ангелов",
        "author": "Бернард Вербер",
        "notes": "",
        "createdAt": "2018-02-03 19:34:22",
        "user": {
            "id": "13935996761918642032-mailru",
            "nickname": "xaytennn",
            "booksCount": 15
        }
    },
    "UJodRF9_1H": {
        "id": "UJodRF9_1H",
        "title": "",
        "author": "",
        "notes": "",
        "createdAt": "2018-02-03 19:33:16",
        "user": {
            "id": "13935996761918642032-mailru",
            "nickname": "xaytennn",
            "booksCount": 15
        }
    },
    "Mgb2Yk-AcO": {
        "id": "Mgb2Yk-AcO",
        "title": "Мы, боги",
        "author": "Бернард Вербер",
        "notes": "",
        "createdAt": "2018-02-03 19:33:02",
        "user": {
            "id": "13935996761918642032-mailru",
            "nickname": "xaytennn",
            "booksCount": 13
        }
    },
    "S-Xza7hwKg": {
        "id": "S-Xza7hwKg",
        "title": "Зеркало Кассандры",
        "author": "Бернард Вербер",
        "notes": "",
        "createdAt": "2018-02-03 19:32:55",
        "user": {
            "id": "13935996761918642032-mailru",
            "nickname": "xaytennn",
            "booksCount": 12
        }
    },
    "WNV9RLjl95": {
        "id": "WNV9RLjl95",
        "title": "Дыхание богов",
        "author": "Бернард Вербер",
        "notes": "",
        "createdAt": "2018-02-03 19:32:40",
        "user": {
            "id": "13935996761918642032-mailru",
            "nickname": "xaytennn",
            "booksCount": 11
        }
    },
    "d20YjKsvNf": {
        "id": "d20YjKsvNf",
        "title": "Тайна богов",
        "author": "Бернард Вербер",
        "notes": "",
        "createdAt": "2018-02-03 19:32:33",
        "user": {
            "id": "13935996761918642032-mailru",
            "nickname": "xaytennn",
            "booksCount": 10
        }
    },
    "AQxsfHR-M5": {
        "id": "AQxsfHR-M5",
        "title": "Социальная инженерия и социальные хакеры",
        "author": "Кузнецов и Симдянов",
        "notes": "",
        "createdAt": "2018-02-03 19:32:25",
        "user": {
            "id": "13935996761918642032-mailru",
            "nickname": "xaytennn",
            "booksCount": 9
        }
    },
    "mclMD-8y9E": {
        "id": "mclMD-8y9E",
        "title": "Повелитель мух",
        "author": "Уильям Голдинг",
        "notes": "",
        "createdAt": "2018-02-03 19:31:59",
        "user": {
            "id": "13935996761918642032-mailru",
            "nickname": "xaytennn",
            "booksCount": 8
        }
    },
    "rn3fmE8laQ": {
        "id": "rn3fmE8laQ",
        "title": "Колыбельная",
        "author": "Чак Паланик",
        "notes": "",
        "createdAt": "2018-02-03 19:31:45",
        "user": {
            "id": "13935996761918642032-mailru",
            "nickname": "xaytennn",
            "booksCount": 7
        }
    },
    "RluTcLl-Ch": {
        "id": "RluTcLl-Ch",
        "title": "Женщина. Где у нее кнопка?",
        "author": "Вис Виталис",
        "notes": "",
        "createdAt": "2018-02-03 19:31:34",
        "user": {
            "id": "13935996761918642032-mailru",
            "nickname": "xaytennn",
            "booksCount": 6
        }
    },
    "5PqD4wpXH5": {
        "id": "5PqD4wpXH5",
        "title": "Отец наших отцов",
        "author": "Бернард Вербер",
        "notes": "",
        "createdAt": "2018-02-03 19:31:17",
        "user": {
            "id": "13935996761918642032-mailru",
            "nickname": "xaytennn",
            "booksCount": 5
        }
    },
    "6GacNz9xZI": {
        "id": "6GacNz9xZI",
        "title": "Рай на заказ",
        "author": "Бернард Вербер",
        "notes": "",
        "createdAt": "2018-02-03 19:31:07",
        "user": {
            "id": "13935996761918642032-mailru",
            "nickname": "xaytennn",
            "booksCount": 4
        }
    },
    "0BXqAe4RD_": {
        "id": "0BXqAe4RD_",
        "title": "Миф о многозадачности. К чему приводит стремление успеть все",
        "author": "Дейв Креншоу",
        "notes": "",
        "createdAt": "2018-02-03 19:30:51",
        "user": {
            "id": "13935996761918642032-mailru",
            "nickname": "xaytennn",
            "booksCount": 3
        }
    },
    "tPH0tLbkc8": {
        "id": "tPH0tLbkc8",
        "title": "Ангелы-хранители",
        "author": "Дин Кунц",
        "notes": "",
        "createdAt": "2018-02-03 19:28:53",
        "user": {
            "id": "13935996761918642032-mailru",
            "nickname": "xaytennn",
            "booksCount": 2
        }
    },
    "HoiBrNomU0": {
        "id": "HoiBrNomU0",
        "title": "Безумный Маро",
        "author": "Дэниел Киз",
        "notes": "",
        "createdAt": "2018-02-03 19:28:34",
        "user": {
            "id": "13935996761918642032-mailru",
            "nickname": "xaytennn",
            "booksCount": 1
        }
    },
    "tuuws854yX": {
        "id": "tuuws854yX",
        "title": "Фиеста",
        "author": "эрнест хемингуэй",
        "notes": "Интересная книга. Запоминается. Поначалу тусовка героев ходят из кафе  в бар и там бухают. Повествование об этом идет день за днем и это надоедает и хочется бросить. Но потом они отправляются в путешествие. на фиесту и тут уже и красивое описание местности, колорит, интересные диалоги. Сама Фиеста ее описание очень запоминающееся. Рекомендую.",
        "createdAt": "2018-02-03 10:39:25",
        "user": {
            "id": "114389869162010721507-google",
            "nickname": "Garri938",
            "booksCount": 41
        }
    },
    "TL-AFU3p0A": {
        "id": "TL-AFU3p0A",
        "title": "Убийство Роджера Экройда",
        "author": "Агата Кристи",
        "notes": "",
        "createdAt": "2018-02-03 09:51:20",
        "user": {
            "id": "114389869162010721507-google",
            "nickname": "Garri938",
            "booksCount": 40
        }
    },
    "rLbBeUCSFc": {
        "id": "rLbBeUCSFc",
        "title": "Узорный покров",
        "author": "Сомерсет Моэм",
        "notes": "Роман. О светском обществе. О женщине и ее взрослении. Как и в других книгах автора здесь есть описание эпидемической болезни.",
        "createdAt": "2018-02-03 09:47:50",
        "user": {
            "id": "114389869162010721507-google",
            "nickname": "Garri938",
            "booksCount": 39
        }
    },
    "NTan3k50PF": {
        "id": "NTan3k50PF",
        "title": "Луна и грош",
        "author": "Сомерсет Моэм",
        "notes": "Роман. Вне сомнения хороший. Про художника о его поиске.",
        "createdAt": "2018-02-03 09:34:46",
        "user": {
            "id": "114389869162010721507-google",
            "nickname": "Garri938",
            "booksCount": 38
        }
    },
    "cm7xiaxPDj": {
        "id": "cm7xiaxPDj",
        "title": "Токийские легенды",
        "author": "Харуки Мураками",
        "notes": "Набор рассказов. Если сравнить с другими его книгами то эта кажется не такой интересной. Дает отвлечься, но не запоминается.",
        "createdAt": "2018-02-03 09:14:54",
        "user": {
            "id": "114389869162010721507-google",
            "nickname": "Garri938",
            "booksCount": 37
        }
    },
    "qjP1mf9mza": {
        "id": "qjP1mf9mza",
        "title": "Цветы в море зла",
        "author": "Цзэн Пу",
        "notes": "Исторический роман о жизни китайских чиновников, которые учатся тусуются и сдают экзамены на мастерство стихосложения. повествование кажется однообразным. Китайские имена героев сложно воспринимаются и запоминаются. Осилил только 1/3.",
        "createdAt": "2018-02-03 09:05:21",
        "user": {
            "id": "114389869162010721507-google",
            "nickname": "Garri938",
            "booksCount": 36
        }
    },
    "oQsUDEPz3d": {
        "id": "oQsUDEPz3d",
        "title": "Доводы рассудка",
        "author": "Джейн Остин",
        "notes": "Поучительный роман. Классическая английская литература из списка лучшие книги обязательные к прочтению. герои запоминающееся и это не один или два персонажа. Само повествование занудное, но главное же в таких романах это поступки и переживание самих героев. Перевод книги на русский тоже радует, потому как не похож на повседневный язык.",
        "createdAt": "2018-02-03 08:34:20",
        "user": {
            "id": "114389869162010721507-google",
            "nickname": "Garri938",
            "booksCount": 35
        }
    },
    "8E6Mevb0dh": {
        "id": "8E6Mevb0dh",
        "title": "Охотники. Мегалиты Империи",
        "author": "Перумов",
        "notes": "",
        "createdAt": "2018-02-03 01:19:39",
        "user": {
            "id": "15649404-vkontakte",
            "nickname": "Mangertus",
            "booksCount": 5
        }
    },
    "kgZz5VIXtM": {
        "id": "kgZz5VIXtM",
        "title": "Level Up. Женский взгляд",
        "author": "Корносенко",
        "notes": "",
        "createdAt": "2018-02-03 01:19:08",
        "user": {
            "id": "15649404-vkontakte",
            "nickname": "Mangertus",
            "booksCount": 4
        }
    },
    "grblsyKsD1": {
        "id": "grblsyKsD1",
        "title": "Продажное королевство",
        "author": "Бардуго",
        "notes": "",
        "createdAt": "2018-02-03 01:18:34",
        "user": {
            "id": "15649404-vkontakte",
            "nickname": "Mangertus",
            "booksCount": 3
        }
    },
    "YA1W0e14Pc": {
        "id": "YA1W0e14Pc",
        "title": "Шестерка воронов",
        "author": "Бардуго",
        "notes": "",
        "createdAt": "2018-02-03 01:17:55",
        "user": {
            "id": "15649404-vkontakte",
            "nickname": "Mangertus",
            "booksCount": 2
        }
    },
    "Uhx82pKgBo": {
        "id": "Uhx82pKgBo",
        "title": "Дикая Россия (фотоальбом)",
        "author": "Иван Дементиевский",
        "notes": "в процессе медитативного листания\n\nhttps://www.ozon.ru/context/detail/id/138795662/",
        "createdAt": "2018-02-03 00:37:52",
        "user": {
            "id": "241974816-vkontakte",
            "nickname": "Ник Литвинов",
            "booksCount": 139
        }
    },
    "mSKdrOATLL": {
        "id": "mSKdrOATLL",
        "title": "Вероника решает умереть",
        "author": "Паоло Коэльо",
        "notes": "Ну вот в духе обычных книг про психбольницы. Вроде неплохо, но сказано уже тысячу раз на страницах других книг. Главная героиня не вызывает особой симпатии, но при этом она вполне реалистична. Понравился конец, кроме того. Как бы не ругали Коэльо за попсовость, но написано неплохо, надо отдать должное",
        "createdAt": "2018-02-02 20:58:23",
        "user": {
            "id": "115226508-vkontakte",
            "nickname": "Saamy",
            "booksCount": 38
        }
    },
    "YxSJHMEUij": {
        "id": "YxSJHMEUij",
        "title": "Ґалапаґос",
        "author": "Курт Воннеґут",
        "notes": "",
        "createdAt": "2018-02-02 11:13:58",
        "user": {
            "id": "116212888203021514442-google",
            "nickname": "parfutik",
            "booksCount": 1
        }
    }
}