{
    "Sn-0mQLn0G": {
        "id": "Sn-0mQLn0G",
        "title": "Мост",
        "author": "Иэн Бэнкс",
        "notes": "Очень сюрреалистичная книга, суть которой становится понятна довольно быстро, но читать и раскручивать цепь событий все равно довольно интересно",
        "createdAt": "2018-06-19 17:41:10",
        "user": {
            "id": "115226508-vkontakte",
            "nickname": "Saamy",
            "booksCount": 49
        }
    },
    "yH00PL8WZl": {
        "id": "yH00PL8WZl",
        "title": "Элегантность ёжика",
        "author": "Мюриель Барбери",
        "notes": "",
        "createdAt": "2018-06-19 17:32:16",
        "user": {
            "id": "115388297580792197479-google",
            "nickname": "Lirenda",
            "booksCount": 1
        }
    },
    "UUT8KzW4H5": {
        "id": "UUT8KzW4H5",
        "title": "Наивно. Супер",
        "author": "Эрленд Лу",
        "notes": "",
        "createdAt": "2018-06-18 18:52:46",
        "user": {
            "id": "108113656204404967440-google",
            "nickname": "Janet",
            "booksCount": 635
        }
    },
    "qWuVkrF6HK": {
        "id": "qWuVkrF6HK",
        "title": "История одного города",
        "author": "Михаил Салтыков-Щедрин",
        "notes": "",
        "createdAt": "2018-06-18 08:55:37",
        "user": {
            "id": "15706320-vkontakte",
            "nickname": "borodach",
            "booksCount": 124
        }
    },
    "7aIqe8A1lk": {
        "id": "7aIqe8A1lk",
        "title": "Удивительная Земля",
        "author": "Сергей Рязанский",
        "notes": "в процессе",
        "createdAt": "2018-06-17 22:13:58",
        "user": {
            "id": "241974816-vkontakte",
            "nickname": "Ник Литвинов",
            "booksCount": 162
        }
    },
    "e_YzEyCRaS": {
        "id": "e_YzEyCRaS",
        "title": "Как пасти котов",
        "author": "Дж.Ханк Рейнвотер",
        "notes": "Книга о том, как нужно руководить программистами. Много полезных и ценных советов, особенно про то, что нужно постоянно контролировать, а еще совершенствоваться и тд и тп. \nТак как повествование хорошо структурировано и весьма концентрировано, то читал долго, понемногу. Далась тяжело, кое-как последнее осилил. Не знаю, советовать ли ее кому-то. Не совсем разделяю позицию автора.",
        "createdAt": "2018-06-17 16:50:32",
        "user": {
            "id": "83820536-yandex",
            "nickname": "lucius",
            "booksCount": 145
        }
    },
    "LxDoD_pkNA": {
        "id": "LxDoD_pkNA",
        "title": "Олеся",
        "author": "Александр Иванович Куприн",
        "notes": "",
        "createdAt": "2018-06-17 16:18:58",
        "user": {
            "id": "252651020-yandex",
            "nickname": "Яна",
            "booksCount": 21
        }
    },
    "t4kKd4ymUR": {
        "id": "t4kKd4ymUR",
        "title": "Гранатовый браслет",
        "author": "Александр Иванович",
        "notes": "",
        "createdAt": "2018-06-17 16:17:11",
        "user": {
            "id": "252651020-yandex",
            "nickname": "Яна",
            "booksCount": 20
        }
    },
    "TQWTy2HJDr": {
        "id": "TQWTy2HJDr",
        "title": "Game of thrones (ENG)",
        "author": "G. Martin",
        "notes": "",
        "createdAt": "2018-06-17 08:10:13",
        "user": {
            "id": "170278332-vkontakte",
            "nickname": "AlexeyNovikov",
            "booksCount": 49
        }
    },
    "4K2O3y7OCM": {
        "id": "4K2O3y7OCM",
        "title": "Мать учения 1-85",
        "author": "Nobody13",
        "notes": "Временная петля, Зориан Казински, Зак Новеда, Куатач-Ичл.\nГодно, прочел залпом",
        "createdAt": "2018-06-17 01:43:48",
        "user": {
            "id": "12282474-vkontakte",
            "nickname": "Tr",
            "booksCount": 67
        }
    },
    "NeibIMkWz-": {
        "id": "NeibIMkWz-",
        "title": "Человек в футляре",
        "author": "Антон Павлович Чехов",
        "notes": "",
        "createdAt": "2018-06-16 14:22:57",
        "user": {
            "id": "252651020-yandex",
            "nickname": "Яна",
            "booksCount": 19
        }
    },
    "3qeCvcKiC6": {
        "id": "3qeCvcKiC6",
        "title": "Смерть чиновника",
        "author": "Антон Павлович Чехов",
        "notes": "",
        "createdAt": "2018-06-16 14:22:13",
        "user": {
            "id": "252651020-yandex",
            "nickname": "Яна",
            "booksCount": 18
        }
    },
    "7A_qG0I3J5": {
        "id": "7A_qG0I3J5",
        "title": "Попрыгунья",
        "author": "Антон Павлович Чехов",
        "notes": "",
        "createdAt": "2018-06-16 14:21:50",
        "user": {
            "id": "252651020-yandex",
            "nickname": "Яна",
            "booksCount": 17
        }
    },
    "1pEDXSoFIV": {
        "id": "1pEDXSoFIV",
        "title": "Пересолил",
        "author": "Антон Павлович Чехов",
        "notes": "",
        "createdAt": "2018-06-16 14:21:35",
        "user": {
            "id": "252651020-yandex",
            "nickname": "Яна",
            "booksCount": 16
        }
    },
    "7qJi4qwjR9": {
        "id": "7qJi4qwjR9",
        "title": "Дом с мезонином",
        "author": "Антон Павлович Чехов",
        "notes": "",
        "createdAt": "2018-06-16 14:19:56",
        "user": {
            "id": "252651020-yandex",
            "nickname": "Яна",
            "booksCount": 15
        }
    },
    "8mfXgiWojt": {
        "id": "8mfXgiWojt",
        "title": "Дама с собачкой",
        "author": "Антон Павлович Чехов",
        "notes": "",
        "createdAt": "2018-06-16 14:19:11",
        "user": {
            "id": "252651020-yandex",
            "nickname": "Яна",
            "booksCount": 14
        }
    },
    "mVm7gZmfj-": {
        "id": "mVm7gZmfj-",
        "title": "О любви",
        "author": "Антон Павлович Чехов",
        "notes": "",
        "createdAt": "2018-06-16 14:18:36",
        "user": {
            "id": "252651020-yandex",
            "nickname": "Яна",
            "booksCount": 13
        }
    },
    "FgHhvSn6mX": {
        "id": "FgHhvSn6mX",
        "title": "Хамелеон",
        "author": "Антон Павлович Чехов",
        "notes": "",
        "createdAt": "2018-06-16 14:18:15",
        "user": {
            "id": "252651020-yandex",
            "nickname": "Яна",
            "booksCount": 12
        }
    },
    "xWmsnJf3-J": {
        "id": "xWmsnJf3-J",
        "title": "Тоска",
        "author": "Антон Павлович Чехов",
        "notes": "",
        "createdAt": "2018-06-16 14:18:01",
        "user": {
            "id": "252651020-yandex",
            "nickname": "Яна",
            "booksCount": 11
        }
    },
    "JomiuZphb9": {
        "id": "JomiuZphb9",
        "title": "Чистый понедельник",
        "author": "Иван Алексеевич Бунин",
        "notes": "",
        "createdAt": "2018-06-16 14:17:04",
        "user": {
            "id": "252651020-yandex",
            "nickname": "Яна",
            "booksCount": 10
        }
    },
    "Bb6fL8BsWF": {
        "id": "Bb6fL8BsWF",
        "title": "Тёмные аллеи",
        "author": "Иван Алексеевич Бунин",
        "notes": "",
        "createdAt": "2018-06-16 14:16:35",
        "user": {
            "id": "252651020-yandex",
            "nickname": "Яна",
            "booksCount": 9
        }
    },
    "PWg5W3gjjx": {
        "id": "PWg5W3gjjx",
        "title": "Мамочка и смысл жизни",
        "author": "Ирвин Ялом",
        "notes": "",
        "createdAt": "2018-06-16 12:26:50",
        "user": {
            "id": "108113656204404967440-google",
            "nickname": "Janet",
            "booksCount": 634
        }
    },
    "dEj-i4rDDF": {
        "id": "dEj-i4rDDF",
        "title": "Не местные",
        "author": "Линор Горалик",
        "notes": "",
        "createdAt": "2018-06-15 15:59:52",
        "user": {
            "id": "108113656204404967440-google",
            "nickname": "Janet",
            "booksCount": 633
        }
    },
    "qjfLw6LVhy": {
        "id": "qjfLw6LVhy",
        "title": "Солнце,старик и девушка",
        "author": "Василий Шукшин",
        "notes": "",
        "createdAt": "2018-06-15 12:23:13",
        "user": {
            "id": "252651020-yandex",
            "nickname": "Яна",
            "booksCount": 8
        }
    },
    "xK6hwaPkMa": {
        "id": "xK6hwaPkMa",
        "title": "Ионыч",
        "author": "Антон Павлович Чехов",
        "notes": "",
        "createdAt": "2018-06-15 12:08:05",
        "user": {
            "id": "252651020-yandex",
            "nickname": "Яна",
            "booksCount": 7
        }
    },
    "9Dp7Rt8BWi": {
        "id": "9Dp7Rt8BWi",
        "title": "Господин из Сан-Франциско",
        "author": "Иван Алексеевич Бунин",
        "notes": "",
        "createdAt": "2018-06-15 09:35:57",
        "user": {
            "id": "252651020-yandex",
            "nickname": "Яна",
            "booksCount": 6
        }
    },
    "MeVfxX0wc7": {
        "id": "MeVfxX0wc7",
        "title": "Толстый и тонкий",
        "author": "Антон Павлович Чехов",
        "notes": "",
        "createdAt": "2018-06-15 09:34:55",
        "user": {
            "id": "252651020-yandex",
            "nickname": "Яна",
            "booksCount": 5
        }
    },
    "8IxYxewoBk": {
        "id": "8IxYxewoBk",
        "title": "Крыжовник",
        "author": "Антон Павлович Чехов",
        "notes": "",
        "createdAt": "2018-06-15 09:34:21",
        "user": {
            "id": "252651020-yandex",
            "nickname": "Яна",
            "booksCount": 4
        }
    },
    "XfS3we9YeJ": {
        "id": "XfS3we9YeJ",
        "title": "Потрет Дориана Грея",
        "author": "Оскар Уайльд",
        "notes": "",
        "createdAt": "2018-06-15 09:32:38",
        "user": {
            "id": "252651020-yandex",
            "nickname": "Яна",
            "booksCount": 3
        }
    },
    "TQ-9nPmFgx": {
        "id": "TQ-9nPmFgx",
        "title": "А зори здесь тихие...",
        "author": "Борис Васильев",
        "notes": "",
        "createdAt": "2018-06-15 09:30:03",
        "user": {
            "id": "252651020-yandex",
            "nickname": "Яна",
            "booksCount": 2
        }
    }
}