{
    "id": "BEXCT60YN1",
    "userId": "333646551-vkontakte",
    "createdAt": "2017-10-06 08:39:21",
    "updatedAt": "2017-10-06 08:39:21",
    "title": "Игры Эндера",
    "author": "Орсон Скотт Кард",
    "priority": 96,
    "notes": "Земля в ожидании очередного вторжения инопланетных захватчиков - жукеров. Действие происходит в школе для одаренных детей, в которой отбирают будущих воинов и командиров звездных эскадр. Роман известен по неудачной экранизации с Гаррисоном Фордом в главной роли"
}